i3wins/__init__.py
i3wins/i3lasts.py
i3wins/i3wins.py
i3wins-0.0.3.dist-info/LICENSE
i3wins-0.0.3.dist-info/METADATA
i3wins-0.0.3.dist-info/WHEEL
i3wins-0.0.3.dist-info/entry_points.txt
i3wins-0.0.3.dist-info/top_level.txt
i3wins-0.0.3.dist-info/RECORD
